{"ERA1" : [
    {
      "NAME" : "Campfire", 
      "OBJECT" : "oCampfire", 
      "SPRITE" : "sCampfire", 
      "SPRITE_ID" : 1, 
      "RESOURCES" : {"0" : 2, "2" : 1, "1" : 1}},
    {
      "NAME" : "Tent", 
      "OBJECT" : "oTent", 
      "SPRITE" : "sTent", 
      "SPRITE_ID" : 0, 
      "RESOURCES" : {"0" : 2, "4" : 2}},
    {
      "NAME" : "Chest", 
      "OBJECT" : "oChest", 
      "SPRITE" : "sSmallChest", 
      "SPRITE_ID" : 0, 
      "RESOURCES" : {}},
    {
      "NAME" : "Fence", 
      "OBJECT" : "oFence", 
      "SPRITE" : "sShortFence", 
      "SPRITE_ID" : 0, 
      "RESOURCES" : {}}
  ]
}